latticeflow/__init__.py
latticeflow/info.py
latticeflow_widgets-0.0.1.dist-info/METADATA
latticeflow_widgets-0.0.1.dist-info/WHEEL
latticeflow_widgets-0.0.1.dist-info/top_level.txt
latticeflow_widgets-0.0.1.dist-info/RECORD
